httpie_http2.py
httpie_http2-0.0.1.dist-info/DESCRIPTION.rst
httpie_http2-0.0.1.dist-info/entry_points.txt
httpie_http2-0.0.1.dist-info/METADATA
httpie_http2-0.0.1.dist-info/metadata.json
httpie_http2-0.0.1.dist-info/RECORD
httpie_http2-0.0.1.dist-info/top_level.txt
httpie_http2-0.0.1.dist-info/WHEEL
